{
  "_meta": {
    "writer": "commons_photo.py",
    "version": 1
  },
  "800px-santa-croce.jpg": {
    "title": "File:Basilica of Santa Croce, Lecce 02.jpg",
    "source_url": "https://upload.wikimedia.org/wikipedia/commons/6/60/Basilica_of_Santa_Croce%2C_Lecce_02.jpg",
    "page_url": "https://commons.wikimedia.org/wiki/File:Basilica_of_Santa_Croce,_Lecce_02.jpg",
    "sha256": "f61251bf5a00bea27800e183e0f5e704074fee3c3e220db0945dfc091f5315d6",
    "width": 800,
    "height": 1183
  },
  "800px-duomo.jpg": {
    "title": "File:Lecce - Campanile del Duomo - 02.jpg",
    "source_url": "https://upload.wikimedia.org/wikipedia/commons/d/d5/Lecce_-_Campanile_del_Duomo_-_02.jpg",
    "page_url": "https://commons.wikimedia.org/wiki/File:Lecce_-_Campanile_del_Duomo_-_02.jpg",
    "sha256": "d940ab680fe199c4113b27efff2ae9d62df3b792f49ae9544131034e3c426b5c",
    "width": 800,
    "height": 1880
  },
  "800px-amphitheatre.jpg": {
    "title": "File:Lecce-anfiteatro-romano.jpg",
    "source_url": "https://upload.wikimedia.org/wikipedia/commons/8/84/Lecce-anfiteatro-romano.jpg",
    "page_url": "https://commons.wikimedia.org/wiki/File:Lecce-anfiteatro-romano.jpg",
    "sha256": "6053f9a7a5ea60fb0606381242dc186aa06b7a81777ec3f9abc41a21781687c4",
    "width": 800,
    "height": 1207
  },
  "800px-castello-lecce.jpg": {
    "title": "File:224 Castello Carlo V, Via XXV Luglio (Lecce), vest\u00edbul.jpg",
    "source_url": "https://upload.wikimedia.org/wikipedia/commons/a/a3/224_Castello_Carlo_V%2C_Via_XXV_Luglio_%28Lecce%29%2C_vest%C3%ADbul.jpg",
    "page_url": "https://commons.wikimedia.org/wiki/File:224_Castello_Carlo_V,_Via_XXV_Luglio_(Lecce),_vest%C3%ADbul.jpg",
    "sha256": "737c164d9bb24c7b25ce599fcc571f082ffdaf8554b0cddfbe2505e889a3035b",
    "width": 800,
    "height": 600
  },
  "800px-rione-monti.jpg": {
    "title": "File:Alberobello - Trulli del Rione Monti - 03.jpg",
    "source_url": "https://upload.wikimedia.org/wikipedia/commons/c/c7/Alberobello_-_Trulli_del_Rione_Monti_-_03.jpg",
    "page_url": "https://commons.wikimedia.org/wiki/File:Alberobello_-_Trulli_del_Rione_Monti_-_03.jpg",
    "sha256": "4dc761f5be7bf6704a56a79e1db5f5390a9acec09a0241211021a2d169c923c3",
    "width": 800,
    "height": 533
  },
  "800px-trullo-sovrano.jpg": {
    "title": "File:Alberobello - Trullo Sovrano - 1.jpg",
    "source_url": "https://upload.wikimedia.org/wikipedia/commons/e/eb/Alberobello_-_Trullo_Sovrano_-_1.jpg",
    "page_url": "https://commons.wikimedia.org/wiki/File:Alberobello_-_Trullo_Sovrano_-_1.jpg",
    "sha256": "ea3db612e8906817cad15a73804ab04bb792eb6688cbd2c854dd12f750375f01",
    "width": 800,
    "height": 449
  },
  "800px-ostuni-cathedral.jpg": {
    "title": "File:Ostuni, cattedrale, esterno 02.jpg",
    "source_url": "https://upload.wikimedia.org/wikipedia/commons/9/96/Ostuni%2C_cattedrale%2C_esterno_02.jpg",
    "page_url": "https://commons.wikimedia.org/wiki/File:Ostuni,_cattedrale,_esterno_02.jpg",
    "sha256": "3ae80ab501752169c362c8db1b3881bd49e20b7f179e73f5f62a1523f190fa2c",
    "width": 800,
    "height": 802
  },
  "800px-grotta-poesia.jpg": {
    "title": "File:Grotta della Poesia (2).jpg",
    "source_url": "https://upload.wikimedia.org/wikipedia/commons/5/58/Grotta_della_Poesia_%282%29.jpg",
    "page_url": "https://commons.wikimedia.org/wiki/File:Grotta_della_Poesia_(2).jpg",
    "sha256": "78de6d8eea03850668d121033247e79caeb91ab695136108353896c049a9650f",
    "width": 800,
    "height": 600
  },
  "800px-otranto-cathedral.jpg": {
    "title": "File:Otranto Cathedral 01.jpg",
    "source_url": "https://upload.wikimedia.org/wikipedia/commons/f/f1/Otranto_Cathedral_01.jpg",
    "page_url": "https://commons.wikimedia.org/wiki/File:Otranto_Cathedral_01.jpg",
    "sha256": "cb09645dd542976b97ee47e16aeae8c1cde42b40026504654ecb4e0bd7bf1c5f",
    "width": 800,
    "height": 557
  },
  "800px-castello-otranto.jpg": {
    "title": "File:049 Castello Aragonese (Otranto), cara oest, Piazza Castello.jpg",
    "source_url": "https://upload.wikimedia.org/wikipedia/commons/5/57/049_Castello_Aragonese_%28Otranto%29%2C_cara_oest%2C_Piazza_Castello.jpg",
    "page_url": "https://commons.wikimedia.org/wiki/File:049_Castello_Aragonese_(Otranto),_cara_oest,_Piazza_Castello.jpg",
    "sha256": "720b41125459c25b2ed07ab3c0081220f94f9c45b12b6fe1d5df82d226f3dd9b",
    "width": 800,
    "height": 600
  },
  "800px-san-pietro.jpg": {
    "title": "File:Chiesa di San Pietro (Otranto) 02.jpg",
    "source_url": "https://upload.wikimedia.org/wikipedia/commons/9/9f/Chiesa_di_San_Pietro_%28Otranto%29_02.jpg",
    "page_url": "https://commons.wikimedia.org/wiki/File:Chiesa_di_San_Pietro_(Otranto)_02.jpg",
    "sha256": "ae90d1c979d1e987a346c552a84467d39f22354b14252c286c23080af5b39e96",
    "width": 800,
    "height": 1120
  },
  "800px-ostuni.jpg": {
    "title": "File:Ostuni col drone.jpg",
    "source_url": "https://upload.wikimedia.org/wikipedia/commons/5/5d/Ostuni_col_drone.jpg",
    "page_url": "https://commons.wikimedia.org/wiki/File:Ostuni_col_drone.jpg",
    "sha256": "81ef821f409deb9c7fe0e0768c17a5985cc0178e454711cf630d8bdc0b265d6a",
    "width": 800,
    "height": 600
  }
}