{
  "_meta": {
    "writer": "create_provenance.py",
    "version": 1
  },
  "800px-arenes-cimiez.jpg": {
    "commons_title": "File:800px-arenes-cimiez.jpg",
    "source_url": "https://commons.wikimedia.org/wiki/File:arenes-cimiez.jpg",
    "sha256": "884258a215d50623851c26df3f34bd600213b8fba9fc18320c81c78205573395"
  },
  "800px-castle-hill.jpg": {
    "commons_title": "File:800px-castle-hill.jpg",
    "source_url": "https://commons.wikimedia.org/wiki/File:castle-hill.jpg",
    "sha256": "9be8d766c8efb0e693a2808c83f80f91674922164e3a86c19411b9b43d530e1d"
  },
  "800px-cours-saleya-market.jpg": {
    "commons_title": "File:800px-cours-saleya-market.jpg",
    "source_url": "https://commons.wikimedia.org/wiki/File:cours-saleya-market.jpg",
    "sha256": "7a37e5b67ed86d4f534e6b9c6d1c6d24fa900664cc86fffdd49b76b7e5cae013"
  },
  "800px-eze-village.jpg": {
    "commons_title": "File:800px-eze-village.jpg",
    "source_url": "https://commons.wikimedia.org/wiki/File:eze-village.jpg",
    "sha256": "8d74afd4cb18f5714393d43f892158bb4b62b84696bcc408e2167a06b8600931"
  },
  "800px-mamac-nice.jpg": {
    "commons_title": "File:800px-mamac-nice.jpg",
    "source_url": "https://commons.wikimedia.org/wiki/File:mamac-nice.jpg",
    "sha256": "9f6f02614181f83c1eaf8ce451523f661fa574e0a16d9dc7f23a5d4b224892f9"
  },
  "800px-monastere-cimiez.jpg": {
    "commons_title": "File:800px-monastere-cimiez.jpg",
    "source_url": "https://commons.wikimedia.org/wiki/File:monastere-cimiez.jpg",
    "sha256": "3ef03a0bae639aa39fc51dff67bd330b9e368e815311ce73e663acaf21c7bd78"
  },
  "800px-musee-beaux-arts-nice.jpg": {
    "commons_title": "File:800px-musee-beaux-arts-nice.jpg",
    "source_url": "https://commons.wikimedia.org/wiki/File:musee-beaux-arts-nice.jpg",
    "sha256": "06262b732e45453cc2777e8eb789198421a4e38b942e881d4a94b0729494f6b3"
  },
  "800px-musee-massena.jpg": {
    "commons_title": "File:800px-musee-massena.jpg",
    "source_url": "https://commons.wikimedia.org/wiki/File:musee-massena.jpg",
    "sha256": "b013d75bee5db9ca5b957a2b59a8402d69df9ae3c2358c38ebb0103d8fbe9e04"
  },
  "800px-place-massena.jpg": {
    "commons_title": "File:800px-place-massena.jpg",
    "source_url": "https://commons.wikimedia.org/wiki/File:place-massena.jpg",
    "sha256": "791060cd321c8bf7c72a1e2d2f604cc7f5ac99906f8340eb4dc76674026bd983"
  },
  "800px-promenade-des-anglais.jpg": {
    "commons_title": "File:800px-promenade-des-anglais.jpg",
    "source_url": "https://commons.wikimedia.org/wiki/File:promenade-des-anglais.jpg",
    "sha256": "896574deb417b77f7e116b41546635203da3b8a9b16ec4cd095a20ca1c48504a"
  },
  "800px-roquebrune-cap-martin.jpg": {
    "commons_title": "File:800px-roquebrune-cap-martin.jpg",
    "source_url": "https://commons.wikimedia.org/wiki/File:roquebrune-cap-martin.jpg",
    "sha256": "66eff3f8f61ad931735a73fd54014948670f2762f0b415cafdee83c3b7726afd"
  },
  "800px-russian-cathedral.jpg": {
    "commons_title": "File:800px-russian-cathedral.jpg",
    "source_url": "https://commons.wikimedia.org/wiki/File:russian-cathedral.jpg",
    "sha256": "878253de30c209887115fd0967d93bd167c78194343fc9e45aa3129e121020ef"
  },
  "800px-vieux-nice.jpg": {
    "commons_title": "File:800px-vieux-nice.jpg",
    "source_url": "https://commons.wikimedia.org/wiki/File:vieux-nice.jpg",
    "sha256": "2745ea60edcc2db1d83e5cdd3ef69d84ec91a920aa6d94108a262431cb77f2d2"
  },
  "800px-villa-ephrussi-rothschild.jpg": {
    "commons_title": "File:800px-villa-ephrussi-rothschild.jpg",
    "source_url": "https://commons.wikimedia.org/wiki/File:villa-ephrussi-rothschild.jpg",
    "sha256": "a0dca54e94f983b726ebb851b315460b6e8ad50866d8a63efca5199e9527d4b1"
  },
  "800px-villefranche-sur-mer.jpg": {
    "commons_title": "File:800px-villefranche-sur-mer.jpg",
    "source_url": "https://commons.wikimedia.org/wiki/File:villefranche-sur-mer.jpg",
    "sha256": "cab9fe02e9b5a0f95e25afe2c6521b1dff3ab7b6be45e4a706193acacbd39c13"
  }
}